pydep_dot_to_uml/__init__.py
pydep_dot_to_uml/dot.py
pydep_dot_to_uml/file.py
pydep_dot_to_uml/py.typed
pydep_dot_to_uml/pydep_dot_to_uml.py
pydep_dot_to_uml/util.py
pydep_dot_to_uml-1.0.3.dist-info/LICENSE
pydep_dot_to_uml-1.0.3.dist-info/METADATA
pydep_dot_to_uml-1.0.3.dist-info/WHEEL
pydep_dot_to_uml-1.0.3.dist-info/entry_points.txt
pydep_dot_to_uml-1.0.3.dist-info/top_level.txt
pydep_dot_to_uml-1.0.3.dist-info/RECORD
